aiomisc_dependency/__init__.py
aiomisc_dependency/plugin.py
aiomisc_dependency/version.py
aiomisc_dependency-0.1.21.dist-info/licenses/COPYING
aiomisc_dependency-0.1.21.dist-info/METADATA
aiomisc_dependency-0.1.21.dist-info/WHEEL
aiomisc_dependency-0.1.21.dist-info/entry_points.txt
aiomisc_dependency-0.1.21.dist-info/top_level.txt
aiomisc_dependency-0.1.21.dist-info/RECORD
