Metadata-Version: 2.4
Name: aiomisc-dependency
Version: 0.1.21
Summary: aiomisc-dependency - dependency injection in aiomisc
Author-email: Yuri Shikanov <dizballanze@gmail.com>
License: MIT
Project-URL: homepage, https://github.com/aiokitchen/aiomisc-dependency
Classifier: Framework :: Pytest
Classifier: Intended Audience :: Developers
Classifier: Natural Language :: Russian
Classifier: Operating System :: MacOS
Classifier: Operating System :: POSIX
Classifier: Programming Language :: Python
Classifier: Programming Language :: Python :: 3
Classifier: Programming Language :: Python :: 3.9
Classifier: Programming Language :: Python :: 3.10
Classifier: Programming Language :: Python :: 3.11
Classifier: Programming Language :: Python :: 3.12
Classifier: Programming Language :: Python :: 3.13
Classifier: Programming Language :: Python :: 3.14
Classifier: Programming Language :: Python :: Implementation :: CPython
Requires-Python: <4.0,>=3.9
License-File: COPYING
Requires-Dist: aiodine~=1.2.9
Requires-Dist: aiomisc>=17
Provides-Extra: test
Requires-Dist: aiomisc-pytest; extra == "test"
Requires-Dist: coverage~=4.5.3; extra == "test"
Requires-Dist: coveralls; extra == "test"
Requires-Dist: pylama; extra == "test"
Requires-Dist: pytest; extra == "test"
Requires-Dist: pytest-cov; extra == "test"
Requires-Dist: setuptools>=65.5.1; extra == "test"
Requires-Dist: tox; extra == "test"
Dynamic: license-file
